{
  "unpublishedPage": {
    "name": "Page1",
    "slug": "page1",
    "layouts": [
      {
        "viewMode": false,
        "dsl": {
          "widgetName": "MainContainer",
          "backgroundColor": "none",
          "rightColumn": 4896,
          "snapColumns": 64,
          "detachFromLayout": true,
          "widgetId": "0",
          "topRow": 0,
          "bottomRow": 920,
          "containerStyle": "none",
          "snapRows": 124,
          "parentRowSpace": 1,
          "type": "CANVAS_WIDGET",
          "canExtend": true,
          "version": 83,
          "minHeight": 1292,
          "dynamicTriggerPathList": [],
          "parentColumnSpace": 1,
          "dynamicBindingPathList": [],
          "leftColumn": 0
        },
        "layoutOnLoadActions": [
          [
            {
              "id": "Page1_ScrapQuery",
              "name": "ScrapQuery",
              "confirmBeforeExecute": false,
              "pluginType": "DB",
              "jsonPathKeys": [],
              "timeoutInMillisecond": 10000
            },
            {
              "id": "Page1_holdquery",
              "name": "holdquery",
              "confirmBeforeExecute": false,
              "pluginType": "DB",
              "jsonPathKeys": [],
              "timeoutInMillisecond": 10000
            }
          ],
          [
            {
              "id": "Page1_Api1",
              "name": "Api1",
              "confirmBeforeExecute": false,
              "pluginType": "API",
              "jsonPathKeys": [
                "serialnoInput.text"
              ],
              "timeoutInMillisecond": 10000
            }
          ]
        ],
        "layoutOnLoadActionErrors": [],
        "validOnPageLoadActions": true,
        "id": "Page1",
        "deleted": false,
        "policies": [],
        "userPermissions": []
      }
    ],
    "userPermissions": [],
    "policies": []
  },
  "deleted": false,
  "gitSyncId": "64e5ad0b8111a90a049d456c_64e5ad0c8111a90a049d456e"
}